photoprism2immich/__init__.py
photoprism2immich/__version__.py
photoprism2immich/immich_api.py
photoprism2immich/migrator.py
photoprism2immich/photoprism2immich.py
photoprism2immich/photoprism_api.py
photoprism2immich-0.4.0.dist-info/LICENSE
photoprism2immich-0.4.0.dist-info/METADATA
photoprism2immich-0.4.0.dist-info/WHEEL
photoprism2immich-0.4.0.dist-info/entry_points.txt
photoprism2immich-0.4.0.dist-info/top_level.txt
photoprism2immich-0.4.0.dist-info/RECORD
