Metadata-Version: 2.1
Name: photoprism2immich
Version: 0.4.0
Summary: Tool to migrate Photoprism library and albums to Immich
Home-page: https://github.com/giuliolibrando/photoprism2immich
Author: Giulio Librando
Author-email: giuliolibrando@gmail.com
License: MIT
Classifier: License :: OSI Approved :: MIT License
Classifier: Programming Language :: Python :: 3
Classifier: Operating System :: OS Independent
License-File: LICENSE
Requires-Dist: requests
